azure/cognitiveservices/personalizer/__init__.py
azure/cognitiveservices/personalizer/personalizer_client.py
azure/cognitiveservices/personalizer/version.py
azure/cognitiveservices/personalizer/models/__init__.py
azure/cognitiveservices/personalizer/models/error_response.py
azure/cognitiveservices/personalizer/models/error_response_py3.py
azure/cognitiveservices/personalizer/models/internal_error.py
azure/cognitiveservices/personalizer/models/internal_error_py3.py
azure/cognitiveservices/personalizer/models/personalizer_client_enums.py
azure/cognitiveservices/personalizer/models/personalizer_error.py
azure/cognitiveservices/personalizer/models/personalizer_error_py3.py
azure/cognitiveservices/personalizer/models/rank_request.py
azure/cognitiveservices/personalizer/models/rank_request_py3.py
azure/cognitiveservices/personalizer/models/rank_response.py
azure/cognitiveservices/personalizer/models/rank_response_py3.py
azure/cognitiveservices/personalizer/models/rankable_action.py
azure/cognitiveservices/personalizer/models/rankable_action_py3.py
azure/cognitiveservices/personalizer/models/ranked_action.py
azure/cognitiveservices/personalizer/models/ranked_action_py3.py
azure/cognitiveservices/personalizer/models/reward_request.py
azure/cognitiveservices/personalizer/models/reward_request_py3.py
azure/cognitiveservices/personalizer/operations/__init__.py
azure/cognitiveservices/personalizer/operations/events_operations.py
azure_cognitiveservices_personalizer-0.1.0.dist-info/METADATA
azure_cognitiveservices_personalizer-0.1.0.dist-info/WHEEL
azure_cognitiveservices_personalizer-0.1.0.dist-info/top_level.txt
azure_cognitiveservices_personalizer-0.1.0.dist-info/RECORD
